fastbloom_rs-0.5.10.dist-info/METADATA
fastbloom_rs-0.5.10.dist-info/WHEEL
fastbloom_rs-0.5.10.dist-info/licenses/LICENSE
fastbloom_rs/__init__.py
fastbloom_rs/fastbloom_rs.abi3.so
fastbloom_rs/fastbloom_rs.pyi
fastbloom_rs/filter.py
fastbloom_rs-0.5.10.dist-info/RECORD
