Metadata-Version: 2.4
Name: fastbloom_rs
Version: 0.5.10
Classifier: Programming Language :: Python
Requires-Dist: pytest<=7.1.2 ; extra == 'test'
Requires-Dist: pybloom-live ; extra == 'test'
Provides-Extra: test
License-File: LICENSE
License-File: LICENSE
Summary: Some fast bloom filter implemented by Rust for Python and Rust! 10x faster than pybloom!
Keywords: bloom-filter,bloom,filter,bloomfilter,probabilistic data structure,counting-bloom-filter
Home-Page: https://github.com/yankun1992/fastbloom
Author: Yan Kun
Author-email: 1939810907@qq.com
Maintainer-email: Yan Kun <1939810907@qq.com>
License: Apache-2.0
Requires-Python: >=3.7
Project-URL: homepage, https://github.com/yankun1992/fastbloom
Project-URL: documentation, https://github.com/yankun1992/fastbloom/blob/main/README.md
Project-URL: repository, https://github.com/yankun1992/fastbloom
